virtual_sq1.py
virtual_sq1-1.1.0.dist-info/LICENSE
virtual_sq1-1.1.0.dist-info/METADATA
virtual_sq1-1.1.0.dist-info/WHEEL
virtual_sq1-1.1.0.dist-info/top_level.txt
virtual_sq1-1.1.0.dist-info/RECORD
